flake8_scrapy.py
finders/__init__.py
finders/domains.py
finders/oldstyle.py
flake8_scrapy-0.0.1.dist-info/METADATA
flake8_scrapy-0.0.1.dist-info/RECORD
flake8_scrapy-0.0.1.dist-info/WHEEL
flake8_scrapy-0.0.1.dist-info/entry_points.txt
flake8_scrapy-0.0.1.dist-info/top_level.txt
