Metadata-Version: 2.1
Name: flake8-scrapy
Version: 0.0.1
Summary: UNKNOWN
Home-page: http://github.com/stummjr/flake8-scrapy
Author: Valdir Stumm Junior
Author-email: stummjr@gmail.com
License: MIT
Platform: UNKNOWN
Classifier: Framework :: Flake8
Classifier: License :: OSI Approved :: MIT License
Classifier: Programming Language :: Python
Classifier: Programming Language :: Python :: 3
Classifier: Programming Language :: Python :: 3.5
Classifier: Programming Language :: Python :: 3.6
Classifier: Programming Language :: Python :: 3.7
Classifier: Topic :: Software Development :: Libraries :: Python Modules
Classifier: Topic :: Software Development :: Quality Assurance
Requires-Dist: flake8
